revision_agent/__init__.py
revision_agent/utils.py
revision_agent-0.1.0.dist-info/METADATA
revision_agent-0.1.0.dist-info/WHEEL
revision_agent-0.1.0.dist-info/RECORD
